[
  {
    "id": 1,
    "question": "Какие технологии вы используете?",
    "answer": "Я работаю с современным стеком: HTML5, CSS3, JavaScript, React, Node.js, MongoDB, AWS и другими."
  },
  {
    "id": 2,
    "question": "Сколько стоит разработка проекта?",
    "answer": "Стоимость зависит от сложности и объёма проекта. Каждый проект оценивается индивидуально. Свяжитесь со мной для обсуждения вашего проекта."
  },
  {
    "id": 3,
    "question": "Какой срок разработки?",
    "answer": "Сроки варьируются от 2 недель до 3 месяцев в зависимости от масштаба проекта и требований."
  },
  {
    "id": 4,
    "question": "Предоставляете ли вы поддержку после запуска?",
    "answer": "Да, я предоставляю бесплатную техническую поддержку в течение 30 дней после запуска, а также опциональное обслуживание."
  },
  {
    "id": 5,
    "question": "Как начать сотрудничество?",
    "answer": "Свяжитесь со мной через форму контактов на сайте, и мы обсудим ваш проект и возможность сотрудничества."
  }
]
